{
  "products": [
    {
      "product_title": "Apple iPhone 15 (128 GB) - Pink",
      "product_url": "https://www.amazon.in/dp/B0CHX3TW6X",
      "platform": "Amazon",
      "original_price": 60000.0,
      "total_discount": 1800.0,
      "effective_price": 58200.0,
      "savings_percentage": 3.0,
      "recommended_card": "ICICI Bank Amazon Pay",
      "card_benefit_description": "5% cashback on Amazon purchases for Prime members, capped at \u20b91800.",
      "credit_card_benefits": {
        "reward_points_earned": 0.0,
        "reward_points_value": 0.0,
        "cashback_earned": 1800.0,
        "effective_cashback_rate": 3.0,
        "annual_fee": "Nil",
        "welcome_offer": "-",
        "lounge_access": "-",
        "other_benefits": "-",
        "total_value_benefit": 1800.0
      },
      "points_calculation_breakdown": "Using Amazon Pay ICICI: 5% cashback on \u20b960,000 Amazon purchase = \u20b93,000, capped at \u20b91,800.",
      "confidence_score": 0.95
    },
    {
      "product_title": "Apple iPhone 15 (128 GB) - Blue",
      "product_url": "https://www.amazon.in/dp/B0CHX2F5QT",
      "platform": "Amazon",
      "original_price": 60300.0,
      "total_discount": 1800.0,
      "effective_price": 58500.0,
      "savings_percentage": 2.985074626865672,
      "recommended_card": "ICICI Bank Amazon Pay",
      "card_benefit_description": "5% cashback on Amazon purchases for Prime members, capped at \u20b91800.",
      "credit_card_benefits": {
        "reward_points_earned": 0.0,
        "reward_points_value": 0.0,
        "cashback_earned": 1800.0,
        "effective_cashback_rate": 2.985074626865672,
        "annual_fee": "Nil",
        "welcome_offer": "-",
        "lounge_access": "-",
        "other_benefits": "-",
        "total_value_benefit": 1800.0
      },
      "points_calculation_breakdown": "Using Amazon Pay ICICI: 5% cashback on \u20b960,300 Amazon purchase = \u20b93,015, capped at \u20b91,800.",
      "confidence_score": 0.95
    },
    {
      "product_title": "Apple iPhone 15 (128 GB) - Green",
      "product_url": "https://www.amazon.in/dp/B0CHX6NQMD",
      "platform": "Amazon",
      "original_price": 60500.0,
      "total_discount": 1800.0,
      "effective_price": 58700.0,
      "savings_percentage": 2.975206611570248,
      "recommended_card": "ICICI Bank Amazon Pay",
      "card_benefit_description": "5% cashback on Amazon purchases for Prime members, capped at \u20b91800.",
      "credit_card_benefits": {
        "reward_points_earned": 0.0,
        "reward_points_value": 0.0,
        "cashback_earned": 1800.0,
        "effective_cashback_rate": 2.975206611570248,
        "annual_fee": "Nil",
        "welcome_offer": "-",
        "lounge_access": "-",
        "other_benefits": "-",
        "total_value_benefit": 1800.0
      },
      "points_calculation_breakdown": "Using Amazon Pay ICICI: 5% cashback on \u20b960,500 Amazon purchase = \u20b93,025, capped at \u20b91,800.",
      "confidence_score": 0.95
    },
    {
      "product_title": "AppleiPhone 15 (128GB, Black)1 Unit - Black",
      "product_url": "https://www.bigbasket.com/pd/40331223/apple-iphone-15-128gb-black/?nc=cl-prod-list&t_pos_sec=1&t_pos_item=1&t_s=iPhone+15+%2528128GB%252C+Black%2529",
      "platform": "Bigbasket",
      "original_price": 61490.0,
      "total_discount": 614.9,
      "effective_price": 60875.1,
      "savings_percentage": 1.0,
      "recommended_card": "HDFC Bank Millennia",
      "card_benefit_description": "1% cashback on all spends.",
      "credit_card_benefits": {
        "reward_points_earned": 0.0,
        "reward_points_value": 0.0,
        "cashback_earned": 614.9,
        "effective_cashback_rate": 1.0,
        "annual_fee": "1,000",
        "welcome_offer": "1000 Cash Points",
        "lounge_access": "8 complimentary domestic lounge visits per year.",
        "other_benefits": "1% fuel surcharge waiver.",
        "total_value_benefit": 614.9
      },
      "points_calculation_breakdown": "Using HDFC Millennia: 1% cashback on \u20b961,490 = \u20b9614.9",
      "confidence_score": 0.95
    },
    {
      "product_title": "Apple iPhone 15 (Blue, 128 GB)",
      "product_url": "https://www.flipkart.com/apple-iphone-15-blue-128-gb/p/itmbf14ef54f645d?pid=MOBGTAGPAQNVFZZY&lid=LSTMOBGTAGPAQNVFZZYQRLPCQ&marketplace=FLIPKART&q=iPhone+15+128GB&store=tyy%2F4io&srno=s_1_1&otracker=search&fm=organic&iid=85f43595-b9ab-494f-ba26-d5a97eba4941.MOBGTAGPAQNVFZZY.SEARCH&ppt=None&ppn=None&ssid=gnvrtq0n4w0000001751641511978&qH=2953a49b03f1f51b",
      "platform": "Flipkart",
      "original_price": 64900.0,
      "total_discount": 649.0,
      "effective_price": 64251.0,
      "savings_percentage": 1.0,
      "recommended_card": "HDFC Bank Millennia",
      "card_benefit_description": "1% cashback on all spends.",
      "credit_card_benefits": {
        "reward_points_earned": 0.0,
        "reward_points_value": 0.0,
        "cashback_earned": 649.0,
        "effective_cashback_rate": 1.0,
        "annual_fee": "1,000",
        "welcome_offer": "1000 Cash Points",
        "lounge_access": "8 complimentary domestic lounge visits per year.",
        "other_benefits": "1% fuel surcharge waiver.",
        "total_value_benefit": 649.0
      },
      "points_calculation_breakdown": "Using HDFC Millennia: 1% cashback on \u20b964,900 = \u20b9649",
      "confidence_score": 0.95
    },
    {
      "product_title": "Apple iPhone 15 (Pink, 128 GB)",
      "product_url": "https://www.flipkart.com/apple-iphone-15-pink-128-gb/p/itm7579ed94ca647?pid=MOBGTAGPNMZA5PU5&lid=LSTMOBGTAGPNMZA5PU5E1UCRJ&marketplace=FLIPKART&q=iPhone+15+128GB&store=tyy%2F4io&srno=s_1_2&otracker=search&fm=organic&iid=85f43595-b9ab-494f-ba26-d5a97eba4941.MOBGTAGPNMZA5PU5.SEARCH&ppt=None&ppn=None&ssid=gnvrtq0n4w0000001751641511978&qH=2953a49b03f1f51b",
      "platform": "Flipkart",
      "original_price": 64900.0,
      "total_discount": 649.0,
      "effective_price": 64251.0,
      "savings_percentage": 1.0,
      "recommended_card": "HDFC Bank Millennia",
      "card_benefit_description": "1% cashback on all spends.",
      "credit_card_benefits": {
        "reward_points_earned": 0.0,
        "reward_points_value": 0.0,
        "cashback_earned": 649.0,
        "effective_cashback_rate": 1.0,
        "annual_fee": "1,000",
        "welcome_offer": "1000 Cash Points",
        "lounge_access": "8 complimentary domestic lounge visits per year.",
        "other_benefits": "1% fuel surcharge waiver.",
        "total_value_benefit": 649.0
      },
      "points_calculation_breakdown": "Using HDFC Millennia: 1% cashback on \u20b964,900 = \u20b9649",
      "confidence_score": 0.95
    },
    {
      "product_title": "Apple iPhone 15 (Black, 128 GB)",
      "product_url": "https://www.flipkart.com/apple-iphone-15-black-128-gb/p/itm6ac6485515ae4?pid=MOBGTAGPTB3VS24W&lid=LSTMOBGTAGPTB3VS24WKFODHL&marketplace=FLIPKART&q=iPhone+15+128GB&store=tyy%2F4io&spotlightTagId=default_FkPickId_tyy%2F4io&srno=s_1_3&otracker=search&fm=organic&iid=85f43595-b9ab-494f-ba26-d5a97eba4941.MOBGTAGPTB3VS24W.SEARCH&ppt=sp&ppn=sp&ssid=gnvrtq0n4w0000001751641511978&qH=2953a49b03f1f51b",
      "platform": "Flipkart",
      "original_price": 64900.0,
      "total_discount": 649.0,
      "effective_price": 64251.0,
      "savings_percentage": 1.0,
      "recommended_card": "HDFC Bank Millennia",
      "card_benefit_description": "1% cashback on all spends.",
      "credit_card_benefits": {
        "reward_points_earned": 0.0,
        "reward_points_value": 0.0,
        "cashback_earned": 649.0,
        "effective_cashback_rate": 1.0,
        "annual_fee": "1,000",
        "welcome_offer": "1000 Cash Points",
        "lounge_access": "8 complimentary domestic lounge visits per year.",
        "other_benefits": "1% fuel surcharge waiver.",
        "total_value_benefit": 649.0
      },
      "points_calculation_breakdown": "Using HDFC Millennia: 1% cashback on \u20b964,900 = \u20b9649",
      "confidence_score": 0.95
    }
  ]
}
